omnibar/__init__.py
omnibar/py.typed
omnibar/version.py
omnibar/core/__init__.py
omnibar/core/benchmarker.py
omnibar/core/types.py
omnibar/integrations/__init__.py
omnibar/integrations/pydantic_ai/__init__.py
omnibar/integrations/pydantic_ai/benchmarker.py
omnibar/logging/__init__.py
omnibar/logging/evaluator.py
omnibar/logging/logger.py
omnibar/logging/simple_ai_logger.py
omnibar/logging/visual_test_clean_print.py
omnibar/objectives/__init__.py
omnibar/objectives/base.py
omnibar/objectives/combined.py
omnibar/objectives/llm_judge.py
omnibar/objectives/output.py
omnibar/objectives/path.py
omnibar/objectives/state.py
omnibar/utils/__init__.py
omnibar-0.2.0.dist-info/licenses/LICENSE
omnibar-0.2.0.dist-info/licenses/NOTICE
omnibar-0.2.0.dist-info/METADATA
omnibar-0.2.0.dist-info/WHEEL
omnibar-0.2.0.dist-info/top_level.txt
omnibar-0.2.0.dist-info/RECORD
