Metadata-Version: 2.4
Name: omnibar
Version: 0.2.0
Summary: Comprehensive AI Agent Benchmarking Framework (OmniBAR)
Author-email: BrainGnosis <dev@braingnosis.ai>
Maintainer-email: BrainGnosis <dev@braingnosis.ai>
License-Expression: Apache-2.0
Project-URL: Homepage, https://github.com/BrainGnosis/OmniBAR
Project-URL: Repository, https://github.com/BrainGnosis/OmniBAR
Project-URL: Documentation, https://github.com/BrainGnosis/OmniBAR#readme
Project-URL: Bug Tracker, https://github.com/BrainGnosis/OmniBAR/issues
Keywords: ai,agent,benchmarking,evaluation,llm,testing,performance
Classifier: Development Status :: 4 - Beta
Classifier: Intended Audience :: Developers
Classifier: Intended Audience :: Science/Research
Classifier: Operating System :: OS Independent
Classifier: Programming Language :: Python :: 3
Classifier: Programming Language :: Python :: 3.10
Classifier: Programming Language :: Python :: 3.11
Classifier: Programming Language :: Python :: 3.12
Classifier: Topic :: Scientific/Engineering :: Artificial Intelligence
Classifier: Topic :: Software Development :: Testing
Classifier: Topic :: Software Development :: Quality Assurance
Requires-Python: >=3.10
License-File: LICENSE
License-File: NOTICE
Requires-Dist: langchain<2.0.0,>=1.0.0
Requires-Dist: langchain_core<2.0.0,>=1.0.0
Requires-Dist: langchain_openai<2.0.0,>=1.0.0
Requires-Dist: numpy<3.0.0,>=2.2.0
Requires-Dist: pydantic<3.0.0,>=2.12.0
Requires-Dist: rich<15.0.0,>=14.2.0
Requires-Dist: tqdm<5.0.0,>=4.67.0
Requires-Dist: typing-extensions>=4.15.0
Provides-Extra: llm
Requires-Dist: langchain<2.0.0,>=1.0.0; extra == "llm"
Requires-Dist: langchain-openai<2.0.0,>=1.0.0; extra == "llm"
Requires-Dist: langchain-core<2.0.0,>=1.0.0; extra == "llm"
Provides-Extra: dev
Requires-Dist: pytest>=8.0.0; extra == "dev"
Requires-Dist: pytest-cov>=4.0.0; extra == "dev"
Requires-Dist: pytest-asyncio>=0.21.0; extra == "dev"
Requires-Dist: black>=23.0.0; extra == "dev"
Requires-Dist: isort>=5.12.0; extra == "dev"
Requires-Dist: flake8>=6.0.0; extra == "dev"
Requires-Dist: mypy>=1.0.0; extra == "dev"
Requires-Dist: pre-commit>=3.0.0; extra == "dev"
Provides-Extra: docs
Requires-Dist: mkdocs>=1.5.0; extra == "docs"
Requires-Dist: mkdocs-material>=9.0.0; extra == "docs"
Requires-Dist: mkdocstrings[python]>=0.22.0; extra == "docs"
Provides-Extra: all
Requires-Dist: omnibar[dev,docs,llm]; extra == "all"
Dynamic: license-file
